COPYING
MANIFEST.in
README.md
setup.py
config/requirements.full.txt
config/requirements.min.txt
config/requirements.mysql.txt
config/requirements.test.txt
config/requirements.txt
config/requirements.win.txt
config/version.txt
config/boot/boot.default.properties
config/boot/boot.docker.properties
config/boot/boot.min.properties
config/boot/boot.sae.properties
config/boot/boot.sqlite.properties
config/boot/boot.test.properties
config/cron/cron.json
config/file/audio.properties
config/file/code.properties
config/file/image.properties
config/file/mime-types.properties
config/file/preview.properties
config/file/text.properties
config/file/video.properties
config/file/zip.properties
config/lang/en.properties
config/lang/zh.properties
config/note/category.ddc.properties
config/note/category.properties
config/note/smart_group.ini
config/plugin/form_plugin.tpl.py
config/plugin/plugin.tpl.py
config/plugin/plugins.ini
config/user/invalid_names.list
config/user/user_config.default.properties
docs/architecture.md
docs/changelog.md
docs/code_style.md
docs/code_style_css.md
docs/commands.md
docs/database.md
docs/db_migrate.md
docs/plugins.md
docs/search_extension.md
docs/upload_to_pip.md
docs/screenshots/architecture.png
docs/screenshots/architecture.svg
docs/screenshots/architecture_2.png
docs/screenshots/command_listdir.png
docs/screenshots/command_rmfolder.png
docs/screenshots/screenshot01.png
docs/screenshots/screenshot02.png
docs/screenshots/screenshot03.png
docs/screenshots/task_web.PNG
docs/screenshots/xnote_v1.2_editor.PNG
docs/screenshots/xnote_v1.2_list.PNG
docs/screenshots/xnote_v1.2_mobile.png
docs/screenshots/xnote_v1.2_search.png
docs/screenshots/xnote_v1.3_desktop01.png
docs/screenshots/xnote_v1.4.png
docs/screenshots/xnote_v1.5.png
docs/screenshots/xnote_v2.0.png
docs/screenshots/xnote_v2.1_home.png
docs/screenshots/xnote_v2.2_20190331.png
docs/screenshots/xnote_v2.3_20190411.png
docs/screenshots/xnote_v2.3_home.png
docs/screenshots/xnote_v2.4_home.png
xnote_web.egg-info/PKG-INFO
xnote_web.egg-info/SOURCES.txt
xnote_web.egg-info/dependency_links.txt
xnote_web.egg-info/top_level.txt
