Metadata-Version: 2.1
Name: xnote-web
Version: 2025.12.15
Summary: xnote-web框架
Author: mark
Author-email: 578749341@qq.com
Classifier: Programming Language :: Python :: 3
Classifier: License :: OSI Approved :: MIT License
Classifier: Operating System :: OS Independent
License-File: COPYING
